device.cp39-win_amd64.pyd
barcap/__init__.py
barcap/__main__.py
barcap/barcode.py
barcap/capture.py
barcap/main.py
barcap/ocr.py
barcap/ocr_plus.py
barcap/path_finder.py
barcap/device_list/.gitignore
barcap/device_list/LICENSE
barcap/device_list/README.md
barcap/device_list/__init__.py
barcap/device_list/__main__.py
barcap/device_list/device.cpp
barcap/device_list/setup.py
barcap/device_list/test.py
barcap/device_list/screenshot/python-list-device.PNG
barcap-0.2.8.dist-info/LICENSE
barcap-0.2.8.dist-info/METADATA
barcap-0.2.8.dist-info/WHEEL
barcap-0.2.8.dist-info/entry_points.txt
barcap-0.2.8.dist-info/top_level.txt
barcap-0.2.8.dist-info/RECORD
