Metadata-Version: 2.1
Name: barcap
Version: 0.2.8
Summary: Extract any barcode using your web camera
Home-page: https://github.com/Barmaley13/barcap
Author: Kirill V. Belyayev
Author-email: kbelyayev@gmail.com
License: MIT
Platform: UNKNOWN
Requires-Python: >=3.6.0
Requires-Dist: opencv-python
Requires-Dist: opencv-contrib-python
Requires-Dist: pyzbar
Requires-Dist: pylibdmtx
Requires-Dist: pytesseract
